graphabc/__init__.py
graphabc/brush.py
graphabc/brush_h.py
graphabc/colors.py
graphabc/colors_h.py
graphabc/context.py
graphabc/event_loop.py
graphabc/events.py
graphabc/events_h.py
graphabc/exports.py
graphabc/keys_h.py
graphabc/main.py
graphabc/mouse_h.py
graphabc/pen.py
graphabc/pen_h.py
graphabc/picture.py
graphabc/picture_h.py
graphabc/point_h.py
graphabc/render_funnel.py
graphabc/render_funnel_h.py
graphabc/shapes.py
graphabc/text.py
graphabc/text_h.py
graphabc/window.py
graphabc/window_h.py
graphabc-0.0.6.dist-info/LICENSE
graphabc-0.0.6.dist-info/METADATA
graphabc-0.0.6.dist-info/WHEEL
graphabc-0.0.6.dist-info/top_level.txt
graphabc-0.0.6.dist-info/RECORD
