Metadata-Version: 2.2
Name: graphabc
Version: 0.0.6
Summary: PascalABC GraphABC module in Python
Home-page: https://github.com/Toideng/python-graphabc
Author: Toideng
Author-email: <toideng@toideng.com>
License: LGPLv3+
Keywords: pascal,pascalabc,pascalabc.net,graphics,education
Classifier: License :: OSI Approved :: GNU Lesser General Public License v3 or later (LGPLv3+)
Classifier: Topic :: Education
Classifier: Topic :: Multimedia :: Graphics
Classifier: Topic :: Software Development :: Libraries :: Python Modules
Classifier: Development Status :: 3 - Alpha
Classifier: Intended Audience :: Education
Classifier: Programming Language :: Pascal
Classifier: Programming Language :: Python
Classifier: Programming Language :: Python :: 3
Classifier: Operating System :: POSIX :: Linux
Classifier: Operating System :: Microsoft :: Windows
Classifier: Typing :: Typed
Requires-Python: >=3.8.1
License-File: LICENSE
Requires-Dist: raylib>=5.5.0.2
Dynamic: author
Dynamic: author-email
Dynamic: classifier
Dynamic: description
Dynamic: description-content-type
Dynamic: home-page
Dynamic: keywords
Dynamic: license
Dynamic: requires-dist
Dynamic: requires-python
Dynamic: summary
